fossilcicli/__init__.py
fossilcicli/__main__.py
fossilcicli/commands.py
fossilcicli/env.py
fossilcicli/git_flow.py
fossilcicli/utils.py
fossilcicli-0.1.23.dist-info/DESCRIPTION.rst
fossilcicli-0.1.23.dist-info/METADATA
fossilcicli-0.1.23.dist-info/RECORD
fossilcicli-0.1.23.dist-info/WHEEL
fossilcicli-0.1.23.dist-info/entry_points.txt
fossilcicli-0.1.23.dist-info/metadata.json
fossilcicli-0.1.23.dist-info/top_level.txt
