Metadata-Version: 2.0
Name: fossilcicli
Version: 0.1.23
Summary: Fossil Bitbucket piplines CLI tool
Home-page: UNKNOWN
Author: UNKNOWN
Author-email: UNKNOWN
License: UNKNOWN
Platform: UNKNOWN
